pyzipcode/__init__.py
pyzipcode/settings.py
pyzipcode/tests.py
pyzipcode/zipcodes.db
pyzipcode3-2.1.dist-info/METADATA
pyzipcode3-2.1.dist-info/RECORD
pyzipcode3-2.1.dist-info/WHEEL
pyzipcode3-2.1.dist-info/top_level.txt
