Metadata-Version: 2.1
Name: pyzipcode3
Version: 2.1
Summary: Search by ZIP Code, Place and Geo data
Home-page: https://www.github.com/dvf/pyzipcode3
Author: Daniel van Flymen
Author-email: vanflymen@gmail.com
License: GPL
Download-URL: https://www.github.com/dvf/pyzipcode3/archive/2.0.tar.gz
Keywords: zip code distance geo
Platform: UNKNOWN
